magictranslator/__init__.py
magictranslator/response.py
magictranslator/translator.py
magictranslator/detector/__init__.py
magictranslator/detector/detector.py
magictranslator/storage/__init__.py
magictranslator/storage/config_storage.py
magictranslator/storage/crypto.py
magictranslator/storage/storage_test.py
magictranslator/translators/__init__.py
magictranslator/translators/aws_api.py
magictranslator/translators/azure_api.py
magictranslator/translators/google_ajax.py
magictranslator/translators/google_api.py
magictranslator/translators/yandex_api.py
tests/__init__.py
tests/test_translator.py
tests/detector/__init__.py
tests/detector/detector_test.py
tests/detector/test_detector.py
tests/translators/__init__.py
tests/translators/aws_api_test.py
tests/translators/google_ajax_test.py
tests/translators/google_api_test.py
tests/translators/test_aws_api.py
tests/translators/test_google_ajax.py
tests/translators/test_google_api.py
tests/translators/test_yandex_api.py
tests/translators/yandex_api_test.py
magictranslator-0.1.0.dist-info/LICENSE
magictranslator-0.1.0.dist-info/METADATA
magictranslator-0.1.0.dist-info/WHEEL
magictranslator-0.1.0.dist-info/top_level.txt
magictranslator-0.1.0.dist-info/RECORD
