Metadata-Version: 2.1
Name: magictranslator
Version: 0.1.0
Summary: Wrapper library for multiple translation APIs
Home-page: https://github.com/c-rainbow/magictranslator
Author: c_rainbow
Author-email: c.rainbow.678@example.com
License: UNKNOWN
Platform: UNKNOWN
Classifier: Programming Language :: Python :: 3
Classifier: License :: OSI Approved :: MIT License
Classifier: Operating System :: OS Independent
Requires-Python: >=3.7
